{
  "parent": "minecraft:recipes/root",
  "criteria": {
    "has_cinnabar": {
      "conditions": {
        "items": [
          {
            "items": [
              "asylumresources:cinnabar"
            ]
          }
        ]
      },
      "trigger": "minecraft:inventory_changed"
    },
    "has_hammers": {
      "conditions": {
        "items": [
          {
            "tag": "neoforge:hammers"
          }
        ]
      },
      "trigger": "minecraft:inventory_changed"
    },
    "has_the_recipe": {
      "conditions": {
        "recipe": "asylumresources:cinnabar_plate"
      },
      "trigger": "minecraft:recipe_unlocked"
    }
  },
  "requirements": [
    [
      "has_cinnabar",
      "has_hammers",
      "has_the_recipe"
    ]
  ],
  "rewards": {
    "recipes": [
      "asylumresources:cinnabar_plate"
    ]
  },
  "sends_telemetry_event": false
}